{
  "type": "minecraft:chest",
  "pools": [
    {
      "bonus_rolls": 0.0,
      "entries": [
        {
          "type": "minecraft:item",
          "functions": [
            {
              "add": false,
              "count": {
                "type": "minecraft:uniform",
                "max": 1.0,
                "min": 0.25
              },
              "function": "minecraft:set_count"
            },
            {
              "enchantment": "minecraft:looting",
              "formula": "minecraft:uniform_bonus_count",
              "function": "minecraft:apply_bonus",
              "parameters": {
                "bonusMultiplier": 1
              }
            }
          ],
          "name": "skyrimcraft:flawed_ruby"
        },
        {
          "type": "minecraft:item",
          "functions": [
            {
              "add": false,
              "count": {
                "type": "minecraft:uniform",
                "max": 1.0,
                "min": 0.25
              },
              "function": "minecraft:set_count"
            },
            {
              "enchantment": "minecraft:looting",
              "formula": "minecraft:uniform_bonus_count",
              "function": "minecraft:apply_bonus",
              "parameters": {
                "bonusMultiplier": 1
              }
            }
          ],
          "name": "skyrimcraft:flawed_emerald"
        },
        {
          "type": "minecraft:item",
          "functions": [
            {
              "add": false,
              "count": {
                "type": "minecraft:uniform",
                "max": 1.0,
                "min": 0.25
              },
              "function": "minecraft:set_count"
            },
            {
              "enchantment": "minecraft:looting",
              "formula": "minecraft:uniform_bonus_count",
              "function": "minecraft:apply_bonus",
              "parameters": {
                "bonusMultiplier": 1
              }
            }
          ],
          "name": "skyrimcraft:flawed_diamond"
        },
        {
          "type": "minecraft:item",
          "functions": [
            {
              "add": false,
              "count": {
                "type": "minecraft:uniform",
                "max": 1.0,
                "min": 0.25
              },
              "function": "minecraft:set_count"
            },
            {
              "enchantment": "minecraft:looting",
              "formula": "minecraft:uniform_bonus_count",
              "function": "minecraft:apply_bonus",
              "parameters": {
                "bonusMultiplier": 1
              }
            }
          ],
          "name": "skyrimcraft:flawless_ruby"
        },
        {
          "type": "minecraft:item",
          "functions": [
            {
              "add": false,
              "count": {
                "type": "minecraft:uniform",
                "max": 1.0,
                "min": 0.25
              },
              "function": "minecraft:set_count"
            },
            {
              "enchantment": "minecraft:looting",
              "formula": "minecraft:uniform_bonus_count",
              "function": "minecraft:apply_bonus",
              "parameters": {
                "bonusMultiplier": 1
              }
            }
          ],
          "name": "skyrimcraft:flawed_garnet"
        },
        {
          "type": "minecraft:item",
          "functions": [
            {
              "add": false,
              "count": {
                "type": "minecraft:uniform",
                "max": 1.0,
                "min": 0.25
              },
              "function": "minecraft:set_count"
            },
            {
              "enchantment": "minecraft:looting",
              "formula": "minecraft:uniform_bonus_count",
              "function": "minecraft:apply_bonus",
              "parameters": {
                "bonusMultiplier": 1
              }
            }
          ],
          "name": "skyrimcraft:flawless_garnet"
        },
        {
          "type": "minecraft:item",
          "functions": [
            {
              "add": false,
              "count": {
                "type": "minecraft:uniform",
                "max": 1.0,
                "min": 0.25
              },
              "function": "minecraft:set_count"
            },
            {
              "enchantment": "minecraft:looting",
              "formula": "minecraft:uniform_bonus_count",
              "function": "minecraft:apply_bonus",
              "parameters": {
                "bonusMultiplier": 1
              }
            }
          ],
          "name": "skyrimcraft:flawed_amethyst"
        }
      ],
      "name": "oresGemPool",
      "rolls": {
        "type": "minecraft:uniform",
        "max": 1.0,
        "min": 0.125
      }
    }
  ],
  "random_sequence": "skyrimcraft:oregemdrops"
}